deepproblog/__init__.py
deepproblog/__main__.py
deepproblog/arithmetic_circuit.py
deepproblog/dataset.py
deepproblog/embeddings.py
deepproblog/evaluate.py
deepproblog/loss.py
deepproblog/model.py
deepproblog/network.py
deepproblog/optimizer.py
deepproblog/query.py
deepproblog/solver.py
deepproblog/tensor.py
deepproblog/train.py
deepproblog/engines/__init__.py
deepproblog/engines/approximate_engine.py
deepproblog/engines/builtins.py
deepproblog/engines/engine.py
deepproblog/engines/exact_engine.py
deepproblog/engines/prolog_engine/__init__.py
deepproblog/engines/prolog_engine/engine.py
deepproblog/engines/prolog_engine/heuristics.py
deepproblog/engines/prolog_engine/swi_program.py
deepproblog/engines/prolog_engine/swip.py
deepproblog/engines/prolog_engine/prolog_files/builtins.pl
deepproblog/engines/prolog_engine/prolog_files/engine_heap.pl
deepproblog/engines/prolog_engine/prolog_files/heuristics_heap.pl
deepproblog/engines/prolog_engine/prolog_files/ucs.pl
deepproblog/engines/prolog_engine/prolog_files/utils.pl
deepproblog/examples/__init__.py
deepproblog/examples/CLUTRR/__init__.py
deepproblog/examples/CLUTRR/architecture.py
deepproblog/examples/CLUTRR/clutrr.py
deepproblog/examples/CLUTRR/model.pl
deepproblog/examples/CLUTRR/model_forward.pl
deepproblog/examples/CLUTRR/data/__init__.py
deepproblog/examples/Coins/__init__.py
deepproblog/examples/Coins/coins.py
deepproblog/examples/Coins/model.pl
deepproblog/examples/Coins/data/__init__.py
deepproblog/examples/Coins/data/dataset.py
deepproblog/examples/Coins/data/generate_data.py
deepproblog/examples/Coins/data/render.py
deepproblog/examples/Coins/data/blender_files/__init__.py
deepproblog/examples/Coins/data/blender_files/render_script.py
deepproblog/examples/Forth/__init__.py
deepproblog/examples/Forth/Add/__init__.py
deepproblog/examples/Forth/Add/add.py
deepproblog/examples/Forth/Add/choose.pl
deepproblog/examples/Forth/Add/data/__init__.py
deepproblog/examples/Forth/Add/data/extract.py
deepproblog-2.0.6.dist-info/LICENSE
deepproblog-2.0.6.dist-info/METADATA
deepproblog-2.0.6.dist-info/WHEEL
deepproblog-2.0.6.dist-info/top_level.txt
deepproblog-2.0.6.dist-info/RECORD
