Metadata-Version: 2.1
Name: deepproblog
Version: 2.0.6
Summary: DeepProbLog: Problog with neural networks
Home-page: https://github.com/ML-KULeuven/deepproblog
Author: DeepProbLog team
Author-email: robin.manhaeve@cs.kuleuven.be
License: Apache Software License
Keywords: prolog probabilistic logic neural-symbolic problog deepproblog
Classifier: Development Status :: 4 - Beta
Classifier: License :: OSI Approved :: Apache Software License
Classifier: Intended Audience :: Science/Research
Classifier: Programming Language :: Python :: 3.9
Classifier: Programming Language :: Prolog
Classifier: Topic :: Scientific/Engineering :: Artificial Intelligence
License-File: LICENSE
Requires-Dist: pysdd
Requires-Dist: problog
Requires-Dist: torch
Requires-Dist: torchvision
Provides-Extra: examples
Requires-Dist: Pillow ; extra == 'examples'
Provides-Extra: tests
Requires-Dist: pytest ; extra == 'tests'
